trimap/__init__.py
trimap/trimap_.py
trimap-1.1.5.dist-info/LICENSE
trimap-1.1.5.dist-info/METADATA
trimap-1.1.5.dist-info/WHEEL
trimap-1.1.5.dist-info/top_level.txt
trimap-1.1.5.dist-info/RECORD
