Metadata-Version: 2.1
Name: trimap
Version: 1.1.5
Summary: TriMap: Large-scale Dimensionality Reduction Using Triplets
Home-page: http://github.com/eamid/trimap
Author: Ehsan Amid
Author-email: eamid@ucsc.edu
License: LICENSE.txt
Keywords: Dimensionality Reduction Triplets t-SNE LargeVis UMAP
Platform: UNKNOWN
Classifier: Intended Audience :: Science/Research
Classifier: Intended Audience :: Developers
Classifier: Programming Language :: C
Classifier: Programming Language :: Python
Classifier: Topic :: Scientific/Engineering
Classifier: Operating System :: Microsoft :: Windows
Classifier: Operating System :: POSIX
Classifier: Operating System :: Unix
Classifier: Operating System :: MacOS
Classifier: Programming Language :: Python :: 3.6
License-File: LICENSE
Requires-Dist: scikit-learn (>=0.16)
Requires-Dist: numba (>=0.34)
Requires-Dist: annoy (>=1.11)
